{
    "fluentMethods": true,
    "relationships": [
        {
            "relationshipType": "many-to-one",
            "relationshipName": "fornecedor",
            "otherEntityName": "fornecedor",
            "otherEntityField": "nome"
        },
        {
            "relationshipType": "many-to-one",
            "relationshipName": "bem",
            "otherEntityName": "bem",
            "otherEntityField": "nome"
        }
    ],
    "fields": [
        {
            "fieldName": "numero",
            "fieldType": "Integer"
        },
        {
            "fieldName": "dataHora",
            "fieldType": "Instant"
        },
        {
            "fieldName": "garantia",
            "fieldType": "Instant"
        },
        {
            "fieldName": "valor",
            "fieldType": "Double"
        }
    ],
    "changelogDate": "20180530011358",
    "entityTableName": "manutencao_bem",
    "dto": "no",
    "pagination": "no",
    "service": "no",
    "jpaMetamodelFiltering": false
}